{

    "Monday": 
    {
      "Breakfast": "IDLI, SAMBAR, CHUTNI, TEA",
      "Lunch": "RICE, ROTI, DALMA, TOMATO KHAJOR KHATA, JEERA ALOO, BADHI CHURA",
      "Snacks": "ALUCHO, TOMATO KETCHUP, COFFEE",
      "Dinner": "RICE, ROTI, DAL ALOO KOBI CURRY, MIX BHAJA, GULAB JAMUN"
    },
    "Tuesday": 
    {
      "Breakfast": "BADA, GHUGUNI, TEA",
      "Lunch": "RICE, ROTI, DALMA, EGG CURRY/ KOTFA CURRY, DAHI SALAD, SRIRAM PAPAD BIG",
      "Snacks": "CORN SALAD, SOUP",
      "Dinner": "HYDRABADI CHICKEN DUM BIRIYANI WITH RAITA, BOIL EGG/ MIX VEG DUM BIRYANI WITH RAITA, PANEER CURRY RASAGOLA"
    },
    "Wednesday": 
    {
      "Breakfast": "FRUIT BREAD, JAM, ALUCHO, BANANA/EGG, TEA",
      "Lunch": "RICE, ROTI, DAL, MUSTARD FISH /MUSHROOM & GREEN PEAS MASALA, SALAD, SRIRAM PAPAD BIG",
      "Snacks": "ALOO PAKUDI, TOMATO SAUCE, COFFEE",
      "Dinner": "FRIED RICE, ROTI, DAL, CHICKEN CHILLY/PALAK PANEER, SEASONAL BHAJA, SALAD"
    },
    "Thursday": 
    {
      "Breakfast": "CHAKULI,GHUGUNI, COFFEE",
      "Lunch": "RICE, ROTI, DAL, CHHOLE PANEER CURRY, SRIRAM PAPAD BIG, SALAD",
      "Snacks": "MAGGI, TEA",
      "Dinner": "RICE, ROTI, DAL, VEG TADKA/EGG TADKA, ALOO JEERA, JALEBI"
    },
    "Friday": 
    {
      "Breakfast": "SANDWICH , TOMATO KETCHUP, ALUCHOP, BANANA/EGG, TEA",
      "Lunch": "RICE, ROTI, DAL, FISH KALIA/MUSHROOM MATAR MASALA, SEASONAL BHAJA,DAHI SALAD",
      "Snacks": "CHOWMINE SAMOSA, COFFEE",
      "Dinner": "RICE, ROTI, DAL, CHICKEN CURRY/ CHHENA CURRY,RICE KHEER, SRIRAM PAPAD BIG"
    },
    "Saturday": 
    {
      "Breakfast": "PLAIN WHITE UPMA,ALOO ONION CURRY,CHATNI, COFFEE",
      "Lunch": "RICE, ROTI, DAL, POTAL PANEER ALOO CURRY, CABBAGE BEANS PEA BHAJA, AMBULA RAI",
      "Snacks": "FRUIT SALAD, TEA",
      "Dinner": "RICE, ROTI, DAL, EGG ALOO MASALA/CHOLE MASALA, FINGER CHIPS, SALAD"
    },
    "Sunday": 
    {
      "Breakfast": "CHOLE BHATURE, COFFEE",
      "Lunch": "VEG DUM BIRYANI, RAITA, CHICKEN /PANEER CURRY, SRIRAM PAPAD BIG",
      "Snacks": "PAMPOI CHAT, ONION, SEV, DAHI PUDINA CHUTNEY, TEA",
      "Dinner": "RICE, ROTI, DAL,EGG POTATO HOMESTYLE CURRY/SOYABEAN ALOO CURRY, SALAD, ICE CREAM"
    }
  }
